{"config":{"output_file":null,"full_docs":false,"pub_only":true,"reachable_only":true,"distro_crate":false,"signatures":false,"borrow_data":false},"version":"0.19.1","compilation":{"directory":"/home/merlin/.cargo/registry/src/github.com-1ecc6299db9ec823/glutin-0.4.9","program":"/home/merlin/.rustup/toolchains/nightly-x86_64-unknown-linux-gnu/bin/rls","arguments":["--crate-name","build_script_build","/home/merlin/.cargo/registry/src/github.com-1ecc6299db9ec823/glutin-0.4.9/build.rs","--json=diagnostic-rendered-ansi","--crate-type","bin","--emit=dep-info,link","-C","embed-bitcode=no","-C","debuginfo=2","-C","metadata=4c135158c969694b","-C","extra-filename=-4c135158c969694b","--out-dir","/home/merlin/Projects/Programming/Rust/tetras/target/rls/debug/build/glutin-4c135158c969694b","-L","dependency=/home/merlin/Projects/Programming/Rust/tetras/target/rls/debug/deps","--extern","gl_generator=/home/merlin/Projects/Programming/Rust/tetras/target/rls/debug/deps/libgl_generator-b8e7b82f24ba0937.rlib","--extern","khronos_api=/home/merlin/Projects/Programming/Rust/tetras/target/rls/debug/deps/libkhronos_api-4a2eccbb177404b8.rlib","--cap-lints","allow","--error-format=json","--sysroot","/home/merlin/.rustup/toolchains/nightly-x86_64-unknown-linux-gnu"],"output":"/home/merlin/Projects/Programming/Rust/tetras/target/rls/debug/build/glutin-4c135158c969694b/build_script_build-4c135158c969694b"},"prelude":{"crate_id":{"name":"build_script_build","disambiguator":[10581703496935166400,6109995755238345619]},"crate_root":"/home/merlin/.cargo/registry/src/github.com-1ecc6299db9ec823/glutin-0.4.9","external_crates":[{"file_name":"/home/merlin/.cargo/registry/src/github.com-1ecc6299db9ec823/glutin-0.4.9/build.rs","num":1,"id":{"name":"std","disambiguator":[761217931017169021,11182540429948991214]}},{"file_name":"/home/merlin/.cargo/registry/src/github.com-1ecc6299db9ec823/glutin-0.4.9/build.rs","num":2,"id":{"name":"core","disambiguator":[2858088706689600179,17176650857302713463]}},{"file_name":"/home/merlin/.cargo/registry/src/github.com-1ecc6299db9ec823/glutin-0.4.9/build.rs","num":3,"id":{"name":"compiler_builtins","disambiguator":[15879356389475821678,5643460802079966270]}},{"file_name":"/home/merlin/.cargo/registry/src/github.com-1ecc6299db9ec823/glutin-0.4.9/build.rs","num":4,"id":{"name":"rustc_std_workspace_core","disambiguator":[8920863043171661139,6394972819860350927]}},{"file_name":"/home/merlin/.cargo/registry/src/github.com-1ecc6299db9ec823/glutin-0.4.9/build.rs","num":5,"id":{"name":"alloc","disambiguator":[7444524629517225000,3862632196027588969]}},{"file_name":"/home/merlin/.cargo/registry/src/github.com-1ecc6299db9ec823/glutin-0.4.9/build.rs","num":6,"id":{"name":"libc","disambiguator":[5618285707243958873,10527758992658711681]}},{"file_name":"/home/merlin/.cargo/registry/src/github.com-1ecc6299db9ec823/glutin-0.4.9/build.rs","num":7,"id":{"name":"unwind","disambiguator":[15786611459077781418,3427959288485188730]}},{"file_name":"/home/merlin/.cargo/registry/src/github.com-1ecc6299db9ec823/glutin-0.4.9/build.rs","num":8,"id":{"name":"cfg_if","disambiguator":[7447291644365204408,1470667821728193545]}},{"file_name":"/home/merlin/.cargo/registry/src/github.com-1ecc6299db9ec823/glutin-0.4.9/build.rs","num":9,"id":{"name":"hashbrown","disambiguator":[6110035509052048891,1769159197608489149]}},{"file_name":"/home/merlin/.cargo/registry/src/github.com-1ecc6299db9ec823/glutin-0.4.9/build.rs","num":10,"id":{"name":"rustc_std_workspace_alloc","disambiguator":[2517392378542245850,1007682534799069383]}},{"file_name":"/home/merlin/.cargo/registry/src/github.com-1ecc6299db9ec823/glutin-0.4.9/build.rs","num":11,"id":{"name":"rustc_demangle","disambiguator":[10841319041269114641,5435836511512932455]}},{"file_name":"/home/merlin/.cargo/registry/src/github.com-1ecc6299db9ec823/glutin-0.4.9/build.rs","num":12,"id":{"name":"addr2line","disambiguator":[11288057705607810041,2650294536215064940]}},{"file_name":"/home/merlin/.cargo/registry/src/github.com-1ecc6299db9ec823/glutin-0.4.9/build.rs","num":13,"id":{"name":"gimli","disambiguator":[3615958118357796166,6340715783279141278]}},{"file_name":"/home/merlin/.cargo/registry/src/github.com-1ecc6299db9ec823/glutin-0.4.9/build.rs","num":14,"id":{"name":"object","disambiguator":[5192402504599619502,9026648258735454425]}},{"file_name":"/home/merlin/.cargo/registry/src/github.com-1ecc6299db9ec823/glutin-0.4.9/build.rs","num":15,"id":{"name":"miniz_oxide","disambiguator":[18157078792379649936,5967302931976128037]}},{"file_name":"/home/merlin/.cargo/registry/src/github.com-1ecc6299db9ec823/glutin-0.4.9/build.rs","num":16,"id":{"name":"adler","disambiguator":[7273518522570529581,7645160771462661682]}},{"file_name":"/home/merlin/.cargo/registry/src/github.com-1ecc6299db9ec823/glutin-0.4.9/build.rs","num":17,"id":{"name":"panic_unwind","disambiguator":[14392049376104722820,4331661258852677409]}},{"file_name":"/home/merlin/.cargo/registry/src/github.com-1ecc6299db9ec823/glutin-0.4.9/build.rs","num":18,"id":{"name":"gl_generator","disambiguator":[14610687417656980725,12015690118997223865]}},{"file_name":"/home/merlin/.cargo/registry/src/github.com-1ecc6299db9ec823/glutin-0.4.9/build.rs","num":19,"id":{"name":"log","disambiguator":[17561866448411810924,4504362296182916005]}},{"file_name":"/home/merlin/.cargo/registry/src/github.com-1ecc6299db9ec823/glutin-0.4.9/build.rs","num":20,"id":{"name":"xml","disambiguator":[4681428226032733884,16144259560736650312]}},{"file_name":"/home/merlin/.cargo/registry/src/github.com-1ecc6299db9ec823/glutin-0.4.9/build.rs","num":21,"id":{"name":"bitflags","disambiguator":[10184662319038632084,16346083109047954384]}},{"file_name":"/home/merlin/.cargo/registry/src/github.com-1ecc6299db9ec823/glutin-0.4.9/build.rs","num":22,"id":{"name":"khronos_api","disambiguator":[8347522324585557620,1838802950292077822]}}],"span":{"file_name":"/home/merlin/.cargo/registry/src/github.com-1ecc6299db9ec823/glutin-0.4.9/build.rs","byte_start":0,"byte_end":12016,"line_start":1,"line_end":187,"column_start":1,"column_end":2}},"imports":[],"defs":[{"kind":"Mod","id":{"krate":0,"index":0},"span":{"file_name":"/home/merlin/.cargo/registry/src/github.com-1ecc6299db9ec823/glutin-0.4.9/build.rs","byte_start":0,"byte_end":12016,"line_start":1,"line_end":187,"column_start":1,"column_end":2},"name":"","qualname":"::","value":"/home/merlin/.cargo/registry/src/github.com-1ecc6299db9ec823/glutin-0.4.9/build.rs","parent":null,"children":[{"krate":0,"index":1},{"krate":0,"index":2},{"krate":0,"index":3},{"krate":0,"index":4},{"krate":0,"index":5},{"krate":0,"index":9},{"krate":0,"index":6},{"krate":0,"index":7},{"krate":0,"index":8}],"decl_id":null,"docs":"","sig":null,"attributes":[]}],"impls":[],"refs":[],"macro_refs":[],"relations":[]}